setup.cfg
setup.py
pylivecap/__init__.py
pylivecap/core.py
pylivecap.egg-info/PKG-INFO
pylivecap.egg-info/SOURCES.txt
pylivecap.egg-info/dependency_links.txt
pylivecap.egg-info/requires.txt
pylivecap.egg-info/top_level.txt