Metadata-Version: 1.0
Name: pylivecap
Version: 0.0.1
Summary: Grabbing livestream frame as image, including YouTube, Twitch...etc
Home-page: https://github.com/pynayzr/livestream-frame-capture
Author: Louie Lu
Author-email: me@louie.lu
License: MIT
Platform: UNKNOWN
